{
  "nodes": [
    {
      "id": "start",
      "type": "start",
      "position": { "x": 0, "y": 77 },
      "data": {
        "type": "start",
        "label": "Start",
        "processName": "Audio Transcribe",
        "initial": {
          "id": "in",
          "label": "Audio Input",
          "fields": [
            {
              "name": "audio",
              "label": "Audio (16 kHz mono WAV)",
              "kind": "file",
              "required": true,
              "accept": "audio/wav,audio/x-wav,audio/wave"
            }
          ]
        }
      }
    },
    {
      "id": "vad",
      "type": "automated_step",
      "slug": "vad",
      "position": { "x": 290, "y": 2 },
      "data": {
        "type": "automated_step",
        "label": "VAD filter",
        "description": "Borrows the uploaded WAV from Start via `{{ start.audio }}` (compiler stages it via StoragePath, runner resolves to a local path). Reads it with the stdlib `wave` module, runs a simple energy-gate VAD over 30 ms frames (pure-Python `audioop` RMS — swap webrtcvad/silero for production), and re-emits ONLY the voiced frames as raw 16-bit PCM over the Data/Out channel `speech` (~100 ms per write). The bulk audio bytes flow out-of-band over the JetStream datastream transport — they NEVER enter the net marking; the net sees only the channel's open + close (docs/25).",
        "channels": [
          {
            "name": "speech",
            "direction": "out",
            "plane": "data",
            "element": { "type": "binary", "content_type": "audio/L16" }
          }
        ],
        "executionSpec": {
          "backendType": "python",
          "entrypoint": "main.py",
          "config": {
            "python": "python3",
            "requirements": ["audioop-lts"],
            "virtualenv": true,
            "sdk": true,
            "inherit_env": true,
            "env": {}
          }
        },
        "output": {
          "id": "out",
          "label": "VAD stats",
          "fields": [
            { "name": "frames_total", "label": "Frames total", "kind": "number" },
            { "name": "frames_voiced", "label": "Frames voiced", "kind": "number" },
            { "name": "sample_rate", "label": "Sample rate", "kind": "number" }
          ]
        }
      }
    },
    {
      "id": "transcribe",
      "type": "automated_step",
      "slug": "transcribe",
      "position": { "x": 856, "y": 0 },
      "data": {
        "type": "automated_step",
        "label": "Transcribe (faster-whisper)",
        "description": "Declares a Data/In channel `speech` wired from the VAD step's open handle. `aithericon.stream('speech')` drains the out-of-band voiced-audio byte stream (starting EARLY, while the VAD step is still producing), reassembles the raw 16-bit PCM, and runs faster-whisper (`tiny`, CPU/int8) over it. Instead of returning one transcript, it EMITS each recognized segment as it is produced onto the Control/Out channel `parts` (`aithericon.out('parts')` → open → item* → close): one bracketed episode, one tiny `{index,text,start,end}` token per segment. The producer does NOT decide the fold — the consumer edge (`join: gather`) collects them in the `collect` step. LIVE-ONLY: first run pip-installs faster-whisper (ctranslate2/numpy) and downloads the `tiny` model (~75 MB) into the venv/HF cache — slow + network-dependent, exceeds the 60 s `mekhan test` cap on a cold run.",
        "channels": [
          {
            "name": "speech",
            "direction": "in",
            "plane": "data",
            "element": { "type": "binary", "content_type": "audio/L16" }
          },
          {
            "name": "parts",
            "direction": "out",
            "plane": "control",
            "element": { "type": "any" }
          }
        ],
        "executionSpec": {
          "backendType": "python",
          "entrypoint": "main.py",
          "config": {
            "python": "python3",
            "requirements": ["faster-whisper", "numpy"],
            "virtualenv": true,
            "sdk": true,
            "inherit_env": true,
            "env": {}
          }
        },
        "output": {
          "id": "out",
          "label": "Transcribe stats",
          "fields": [
            { "name": "segment_count", "label": "Segments emitted", "kind": "number" },
            { "name": "seconds", "label": "Audio seconds", "kind": "number" }
          ]
        }
      }
    },
    {
      "id": "collect",
      "type": "automated_step",
      "slug": "collect",
      "position": { "x": 1166, "y": 33 },
      "data": {
        "type": "automated_step",
        "label": "Collect transcript",
        "description": "Consumes the transcribe step's Control channel `parts` with `join: gather`, so the compiler's gather barrier re-orders the emitted segments by index and parks the whole collection as `{ output: [<segment>, ...] }` — fed in as this step's input token. Reads the list off `input.output`, concatenates the segment texts in order, and emits the complete `transcript` (plus `segment_count` and total `seconds`). This is the consumer-side fold: the producer just emitted a stream, the join discipline lives on the edge.",
        "channels": [],
        "executionSpec": {
          "backendType": "python",
          "entrypoint": "main.py",
          "config": {
            "python": "python3",
            "requirements": [],
            "virtualenv": false,
            "sdk": true,
            "inherit_env": true,
            "env": {}
          }
        },
        "output": {
          "id": "out",
          "label": "Transcript",
          "fields": [
            { "name": "transcript", "label": "Transcript", "kind": "text" },
            { "name": "segment_count", "label": "Segments", "kind": "number" },
            { "name": "seconds", "label": "Audio seconds", "kind": "number" }
          ]
        }
      }
    },
    {
      "id": "end",
      "type": "end",
      "position": { "x": 1476, "y": 50 },
      "data": {
        "type": "end",
        "label": "Done",
        "resultMapping": [
          { "targetField": "transcript", "expression": "collect.transcript" },
          { "targetField": "segment_count", "expression": "collect.segment_count" },
          { "targetField": "frames_voiced", "expression": "vad.frames_voiced" }
        ]
      }
    }
  ],
  "edges": [
    { "id": "e_start_vad", "source": "start", "target": "vad", "targetHandle": "in", "type": "sequence" },
    { "id": "e_vad_speech_transcribe", "source": "vad", "sourceHandle": "speech", "target": "transcribe", "targetHandle": "speech", "type": "sequence" },
    { "id": "e_transcribe_parts_collect", "source": "transcribe", "sourceHandle": "parts", "target": "collect", "targetHandle": "in", "type": "sequence", "join": "gather" },
    { "id": "e_collect_end", "source": "collect", "target": "end", "targetHandle": "in", "type": "sequence" }
  ]
}
